ey/__init__.py
ey-0.3.5.dist-info/LICENSE
ey-0.3.5.dist-info/METADATA
ey-0.3.5.dist-info/WHEEL
ey-0.3.5.dist-info/top_level.txt
ey-0.3.5.dist-info/RECORD
